1build-1.1.1.data/scripts/1build
onebuild/__init__.py
onebuild/__main__.py
onebuild/action_to_command_lookup.py
onebuild/command.py
onebuild/config_parser.py
onebuild/file_writer.py
onebuild/help_command.py
onebuild/init_command.py
onebuild/input_parser.py
onebuild/list_command.py
onebuild/main.py
onebuild/perform_command.py
onebuild/predefined_actions.py
onebuild/project.py
onebuild/utils.py
onebuild/version_command.py
1build-1.1.1.dist-info/LICENSE
1build-1.1.1.dist-info/METADATA
1build-1.1.1.dist-info/WHEEL
1build-1.1.1.dist-info/top_level.txt
1build-1.1.1.dist-info/RECORD
