Metadata-Version: 2.1
Name: 1build
Version: 1.1.1
Summary: Frictionless way of managing project-specific commands.
Home-page: https://github.com/gopinath-langote/1build
Author: Gopinath Langote
Author-email: gopinathlangote11@gmail.com
License: MIT License
Platform: UNKNOWN
Classifier: Programming Language :: Python :: 3.5
Classifier: Programming Language :: Python :: 3.6
Classifier: Programming Language :: Python :: 3.7
Classifier: License :: OSI Approved :: MIT License
Classifier: Topic :: Software Development :: Build Tools
Classifier: Intended Audience :: Developers
Classifier: Operating System :: OS Independent
Requires-Dist: ruamel.yaml (>=0.15.97)
